gammaALPs/__init__.py
gammaALPs/_version.py
gammaALPs/core.py
gammaALPs/version.py
gammaALPs/base/__init__.py
gammaALPs/base/environs.py
gammaALPs/base/transfer.py
gammaALPs/bfields/__init__.py
gammaALPs/bfields/cell.py
gammaALPs/bfields/gauss.py
gammaALPs/bfields/gmf.py
gammaALPs/bfields/jet.py
gammaALPs/bfields/struc.py
gammaALPs/nel/__init__.py
gammaALPs/nel/icm.py
gammaALPs/nel/jet.py
gammaALPs/utils/__init__.py
gammaALPs/utils/interp2d.py
gammaALPs/utils/trafo.py
tests/__init__.py
tests/test_combined_modules.py
tests/test_conversion.py
tests/test_gmf_models.py
gammaALPs-0.4.0.dist-info/LICENSE
gammaALPs-0.4.0.dist-info/METADATA
gammaALPs-0.4.0.dist-info/WHEEL
gammaALPs-0.4.0.dist-info/top_level.txt
gammaALPs-0.4.0.dist-info/RECORD
