Metadata-Version: 2.1
Name: gammaALPs
Version: 0.4.0
Summary: Python code to calculate the conversion probability between photons and axions / axion-likeparticles in astrophysical magnetic fields
Home-page: https://github.com/me-manu/gammaALPs
Author: Manuel Meyer
Author-email: me.manu@gmx.net
License: BSD
Keywords: gamma-ray astronomy,particle physics,axions
Classifier: Development Status :: 4 - Beta
Classifier: Intended Audience :: Science/Research
Classifier: Topic :: Scientific/Engineering :: Astronomy
Classifier: License :: OSI Approved :: BSD License
Classifier: Programming Language :: Python :: 3.6
Classifier: Programming Language :: Python :: 3.7
Classifier: Programming Language :: Python :: 3.8
License-File: LICENSE
Requires-Dist: numpy >=1.19
Requires-Dist: scipy >=1.5
Requires-Dist: numba >=0.51
Requires-Dist: astropy >=4.0
Requires-Dist: ebltable >=0.5
